group_sense/__init__.py
group_sense/message.py
group_sense/reasoner/__init__.py
group_sense/reasoner/base.py
group_sense/reasoner/concurrent.py
group_sense/reasoner/default.py
group_sense/reasoner/prompt.py
group_sense-0.0.4.dist-info/METADATA
group_sense-0.0.4.dist-info/WHEEL
group_sense-0.0.4.dist-info/licenses/LICENSE
group_sense-0.0.4.dist-info/RECORD
