Metadata-Version: 2.4
Name: group-sense
Version: 0.0.4
Summary: Group Sense
Author-email: Martin Krasser <martin@gradion.ai>
License-Expression: Apache-2.0
License-File: LICENSE
Requires-Python: <3.15,>=3.11
Requires-Dist: google-genai>=1.56.0
Requires-Dist: pydantic-ai>=1.36.0
